[
    {

        "type" : "chairs",
        "resources" : [
            {
                "heading" : "UK Therapy Services Talk Chairs",
                "subheading" : "Our Occupational Therapist",
                "contentSrc": "wlRVdd9s174",
                "video": true,
                "url" : ""
            },
            {
                "heading" : "How We Make Your Chair",
                "subheading" : "British Made",
                "contentSrc": "u9-WpUGw0NM",
                "video": true,
                "url" : ""
            },
            {
                "heading" : "Unique High Leg Lift",
                "subheading" : "The Oak Tree Touch",
                "contentSrc": "vlsfU4fdZmk",
                "video": true,
                "url" : ""
            }
        ]
    } ,
    {

        "type" : "beds",
        "resources" : [  
    {
        "heading" : "UK Therapy Services Talk Beds",
        "subheading" : "Our Occupational Therapist",
        "contentSrc": "oi_n7knzghs",
        "video": true,
        "url" : ""
    },
    {
        "heading" : "How We Make Your Bed",
        "subheading" : "British Made",
        "contentSrc": "731h3uxBtKA",
        "video": true,
        "url" : ""
    },
    {
        "heading" : "Unique High Leg Lift",
        "subheading" : "Bed Hand Control",
        "contentSrc": "X3rvIblAXMc",
        "video": true,
        "url" : ""
    }]
    },
    {

        "type" : "bathlifts",
        "resources" : [  
    {
        "heading" : "The Oak Tree Vision",
        "subheading" : "Your Comfort is our strength",
        "contentSrc": "/images/resources/oak-tree-vision-bath-lift.png",
        "video": false,
        "url": "/about"
    },
    {
        "heading" : "How We Make Your Bath lift",
        "subheading" : "British Made",
        "contentSrc": "rIr46QkfmIE",
        "video": true,
        "url" : ""
    },
    {
        "heading" : "Frequently Asked Questions",
        "subheading" : "Bed Hand Control",
        "contentSrc": "/images/resources/faqs.jpeg",
        "video": false,
        "url" : "/faqs"
    }]
    },
    {

        "type" : "about",
        "resources" : [  
            {
                "heading" : "UK Therapy Services Talk Chairs",
                "subheading" : "Our Occupational Therapist",
                "contentSrc": "/images/resources/sam-shann.png",
                "video": false,
                "url" : "/occupational-therapist"
            },
            {
                "heading" : "How We Make Our Products",
                "subheading" : "British Made",
                "contentSrc": "/images/resources/british-made.png",
                "video": false,
                "url" : "/british-made"
            },
            {
                "heading" : "£200 Trade In Offer",
                "subheading" : "Supporting the British Heart Foundation",
                "contentSrc": "/images/resources/trade-in.png",
                "video": false,
                "url" : "/trade-in"
            }]
    }
]